BUILDBOT.txt
CONTRIBUTORS.txt
HISTORY.txt
LICENSE
MANIFEST.in
README.txt
SPLITTING-PROPOSAL.txt
SPRINT-TODO.txt
TRUNK.txt
bootstrap.py
buildout.cfg
setup.py
ZopeSkel.egg-info/PKG-INFO
ZopeSkel.egg-info/SOURCES.txt
ZopeSkel.egg-info/dependency_links.txt
ZopeSkel.egg-info/entry_points.txt
ZopeSkel.egg-info/not-zip-safe
ZopeSkel.egg-info/requires.txt
ZopeSkel.egg-info/top_level.txt
ez_setup/README.txt
ez_setup/__init__.py
zopeskel/__init__.py
zopeskel/abstract_buildout.py
zopeskel/abstract_zope.py
zopeskel/archetype.py
zopeskel/base.py
zopeskel/basic_namespace.py
zopeskel/basic_zope.py
zopeskel/hosting.py
zopeskel/interfaces.py
zopeskel/kss_plugin.py
zopeskel/nested_namespace.py
zopeskel/plone.py
zopeskel/plone25_buildout.py
zopeskel/plone25_theme.py
zopeskel/plone2_theme.py
zopeskel/plone3_buildout.py
zopeskel/plone3_portlet.py
zopeskel/plone3_theme.py
zopeskel/plone4_buildout.py
zopeskel/plone_app.py
zopeskel/plone_pas.py
zopeskel/recipe.py
zopeskel/silva_buildout.py
zopeskel/ui.py
zopeskel/vars.py
zopeskel/zope2_buildout.py
zopeskel/zopeskel_script.py
zopeskel/docs/archetypes.txt
zopeskel/docs/atschema.txt
zopeskel/docs/basic_namespace.txt
zopeskel/docs/basic_zope.txt
zopeskel/docs/kss_plugin.txt
zopeskel/docs/localcommands.txt
zopeskel/docs/nested_namespace.txt
zopeskel/docs/plone.txt
zopeskel/docs/plone25_buildout.txt
zopeskel/docs/plone25_theme.txt
zopeskel/docs/plone2_theme.txt
zopeskel/docs/plone3_buildout.txt
zopeskel/docs/plone3_portlet.txt
zopeskel/docs/plone3_theme.txt
zopeskel/docs/plone4_buildout.txt
zopeskel/docs/plone_app.txt
zopeskel/docs/plone_pas.txt
zopeskel/docs/recipe.txt
zopeskel/docs/silva_buildout.txt
zopeskel/localcommands/README.txt
zopeskel/localcommands/__init__.py
zopeskel/localcommands/archetype.py
zopeskel/localcommands/plone.py
zopeskel/localcommands/plone_pas.py
zopeskel/localcommands/templates/archetype/atschema/content/+content_class_filename+.py_insert
zopeskel/localcommands/templates/archetype/atschema/content/messagefactory_insert.txt_insert
zopeskel/localcommands/templates/archetype/atschema/content/schema_field_bridge.txt_insert
zopeskel/localcommands/templates/archetype/atschema/interfaces/+interface_name+.py_insert
