Metadata-Version: 1.0
Name: ZopeSkel
Version: 2.20
Summary: Templates and code generator for quickstarting Plone / Zope projects.
Home-page: http://svn.plone.org/svn/collective/ZopeSkel/trunk
Author: Cris Ewing
Author-email: cewing@uw.edu
License: MIT
Keywords: web zope command-line skeleton project
Platform: UNKNOWN
Classifier: Development Status :: 5 - Production/Stable
Classifier: Framework :: Zope2
Classifier: Framework :: Zope3
Classifier: Framework :: Plone
Classifier: Intended Audience :: Developers
Classifier: License :: OSI Approved :: MIT License
Classifier: Programming Language :: Python
Classifier: Topic :: Internet :: WWW/HTTP
Classifier: Topic :: Internet :: WWW/HTTP :: Dynamic Content
